rds_graphile_worker_client/__init__.py
rds_graphile_worker_client/client.py
rds_graphile_worker_client/package_version.py
rds_graphile_worker_client/rds-ca-2019-root.pem
rds_graphile_worker_client-0.1.1.dist-info/METADATA
rds_graphile_worker_client-0.1.1.dist-info/WHEEL
rds_graphile_worker_client-0.1.1.dist-info/top_level.txt
rds_graphile_worker_client-0.1.1.dist-info/RECORD
