Metadata-Version: 2.1
Name: rds-graphile-worker-client
Version: 0.1.1
Summary: A small, simple client for adding jobs to the graphile-worker job queue on RDS postgresql database
Home-page: https://github.com/curvewise/python-rds-graphile-worker-client
Author: Curvewise
Author-email: jacob@curvewise.com
License: UNKNOWN
Project-URL: Issue Tracker, https://github.com/curvewise/python-rds-graphile-worker-client/issues
Platform: UNKNOWN
Classifier: Development Status :: 3 - Alpha
Classifier: Intended Audience :: Other Audience
Classifier: Intended Audience :: Science/Research
Classifier: License :: OSI Approved :: MIT License
Classifier: Operating System :: OS Independent
Classifier: Programming Language :: Python :: 3
Classifier: Topic :: Artistic Software
Classifier: Topic :: Multimedia :: Graphics :: 3D Modeling
Classifier: Topic :: Scientific/Engineering :: Visualization
Requires-Dist: boto3 (<2,>=1.16.25)
Requires-Dist: psycopg2 (<3,>=2.8.6)
